freediscovery/__init__.py
freediscovery/__main__.py
freediscovery/_version.py
freediscovery/base.py
freediscovery/categorization.py
freediscovery/cli.py
freediscovery/datasets.py
freediscovery/email_threading.py
freediscovery/exceptions.py
freediscovery/feature_weighting.py
freediscovery/ingestion.py
freediscovery/interpretation.py
freediscovery/io.py
freediscovery/lsi.py
freediscovery/metrics.py
freediscovery/neighbors.py
freediscovery/pipeline.py
freediscovery/preprocessing.py
freediscovery/search.py
freediscovery/sklearn_compat.py
freediscovery/stop_words.py
freediscovery/text.py
freediscovery/utils.py
freediscovery/viz.py
freediscovery/cluster/__init__.py
freediscovery/cluster/base.py
freediscovery/cluster/birch.py
freediscovery/cluster/dendrogram.py
freediscovery/cluster/hierarchy.py
freediscovery/cluster/optimal_sampling.py
freediscovery/cluster/utils.py
freediscovery/data/20_newsgroups_3categories.pkl.xz
freediscovery/data/20_newsgroups_micro.pkl
freediscovery/data/ds_001/ground_truth_file.txt
freediscovery/data/ds_001/features/0.7.47.101442_features.txt
freediscovery/data/ds_001/raw/0.7.47.101442.txt
freediscovery/data/ds_001/raw/0.7.47.117435.txt
freediscovery/data/ds_001/raw/0.7.6.28635.txt
freediscovery/data/ds_001/raw/0.7.6.28636.txt
freediscovery/data/ds_001/raw/0.7.6.28637.txt
freediscovery/data/ds_001/raw/0.7.6.28638.txt
freediscovery/data/ds_002/raw/0.7.47.1295128.1.txt
freediscovery/data/ds_002/raw/0.7.47.1295194.2.txt
freediscovery/data/ds_002/raw/0.7.47.341516.1.txt
freediscovery/data/ds_002/raw/0.7.47.812312.txt
freediscovery/data/ds_002/raw/0.7.6.555759.1.txt
freediscovery/data/ds_002/raw/0.7.6.555956.1.txt
freediscovery/data/ds_lsi_birch/data.npy
freediscovery/data/fedora-devel-list-2008-October/1
freediscovery/data/fedora-devel-list-2008-October/2
freediscovery/data/fedora-devel-list-2008-October/3
freediscovery/data/fedora-devel-list-2008-October/4
freediscovery-1.3.0.dist-info/DESCRIPTION.rst
freediscovery-1.3.0.dist-info/METADATA
freediscovery-1.3.0.dist-info/RECORD
freediscovery-1.3.0.dist-info/WHEEL
freediscovery-1.3.0.dist-info/entry_points.txt
freediscovery-1.3.0.dist-info/metadata.json
freediscovery-1.3.0.dist-info/top_level.txt
