Metadata-Version: 2.0
Name: freediscovery
Version: 1.3.0
Summary: Open source software for E-Discovery and Information Retrieval
Home-page: https://github.com/FreeDiscovery/FreeDiscovery
Author: Grossman Labs
Author-email: UNKNOWN
License: BSD
Keywords: information-retrieval machine-learning text-classification
Platform: UNKNOWN
Classifier: Development Status :: 4 - Beta
Classifier: Intended Audience :: Information Technology
Classifier: Intended Audience :: Legal Industry
Classifier: License :: OSI Approved :: BSD License
Classifier: Programming Language :: Python :: 2
Classifier: Programming Language :: Python :: 2.7
Classifier: Programming Language :: Python :: 3
Classifier: Programming Language :: Python :: 3.5
Classifier: Programming Language :: Python :: 3.6
Classifier: Operating System :: OS Independent
Classifier: Topic :: Scientific/Engineering :: Artificial Intelligence
Classifier: Topic :: Text Processing :: General
Provides-Extra: core
Requires-Dist: numpy (>=1.10.1); extra == 'core'
Requires-Dist: pandas (>=0.18.0,<0.21); extra == 'core'
Requires-Dist: scikit-learn (>=0.18.0); extra == 'core'
Requires-Dist: scipy (>=0.16.1); extra == 'core'
Provides-Extra: engine
Requires-Dist: flask (>=0.12.0); extra == 'engine'
Requires-Dist: flask-apispec (>=0.3.2); extra == 'engine'
Requires-Dist: marshmallow (>=2.12.2); extra == 'engine'
Requires-Dist: nltk (>=3.2.1); extra == 'engine'
Requires-Dist: numpy (>=1.10.1); extra == 'engine'
Requires-Dist: pandas (>=0.18.0,<0.21); extra == 'engine'
Requires-Dist: pytest (>=3.0.1); extra == 'engine'
Requires-Dist: requests (>=2.7.0); extra == 'engine'
Requires-Dist: scikit-learn (>=0.18.0); extra == 'engine'
Requires-Dist: scipy (>=0.16.1); extra == 'engine'
Requires-Dist: webargs (>=1.5.3); extra == 'engine'
